eqtk/__init__.py
eqtk/checks.py
eqtk/constants.py
eqtk/diagnostics.py
eqtk/linalg.py
eqtk/linalg_jax.py
eqtk/numba_check.py
eqtk/parsers.py
eqtk/solvers.py
eqtk/testcases.py
eqtk/trust_region.py
eqtk-0.1.4.dist-info/LICENSE.md
eqtk-0.1.4.dist-info/METADATA
eqtk-0.1.4.dist-info/WHEEL
eqtk-0.1.4.dist-info/top_level.txt
eqtk-0.1.4.dist-info/RECORD
