Metadata-Version: 2.1
Name: eqtk
Version: 0.1.4
Summary: Equilibrium toolkit
Home-page: https://eqtk.github.io/
Download-URL: https://github.com/justinbois/eqtk/tarball/0.1.4
Author: Justin Bois
Author-email: bois@caltech.edu
License: MIT
Classifier: Development Status :: 4 - Beta
Classifier: Intended Audience :: Developers
Classifier: Programming Language :: Python :: 3
License-File: LICENSE.md
Requires-Dist: numpy
Requires-Dist: numba
Requires-Dist: pandas
